micro_trainer_transformers/__init__.py
micro_trainer_transformers/arguments.py
micro_trainer_transformers/base.py
micro_trainer_transformers/core_args.py
micro_trainer_transformers/core_logger.py
micro_trainer_transformers/core_optim.py
micro_trainer_transformers/core_train.py
micro_trainer_transformers/core_trainer.py
micro_trainer_transformers/sentence_trainer.py
micro_trainer_transformers/trainer.py
micro_trainer_transformers/utils.py
micro_trainer_transformers/collators/__init__.py
micro_trainer_transformers/collators/albert_collator.py
micro_trainer_transformers-0.1.2.dist-info/LICENSE
micro_trainer_transformers-0.1.2.dist-info/METADATA
micro_trainer_transformers-0.1.2.dist-info/WHEEL
micro_trainer_transformers-0.1.2.dist-info/entry_points.txt
micro_trainer_transformers-0.1.2.dist-info/top_level.txt
micro_trainer_transformers-0.1.2.dist-info/RECORD
