Metadata-Version: 2.1
Name: micro-trainer-transformers
Version: 0.1.2
Summary: Micro version train modules Transformers trainer....
Home-page: https://github.com/utrobinmv/micro_trainer_transformers
Author: Utrobin Mikhail
Author-email: utrobinmv@yandex.ru
License: Apache
Platform: UNKNOWN
Classifier: Development Status :: 3 - Alpha
Classifier: Programming Language :: Python :: 3
Classifier: License :: OSI Approved :: MIT License
Classifier: Operating System :: OS Independent
Requires-Dist: pytorch-lightning (<=1.9.5)
Requires-Dist: torch
Requires-Dist: datasets
